pyasynctracker/__init__.py
pyasynctracker/scraper.py
pyasynctracker/utils.py
pyasynctracker-0.3.1.dist-info/LICENSE
pyasynctracker-0.3.1.dist-info/METADATA
pyasynctracker-0.3.1.dist-info/WHEEL
pyasynctracker-0.3.1.dist-info/RECORD
