Metadata-Version: 2.1
Name: PyAsyncTracker
Version: 0.3.1
Summary: Asynchronous scraping library for torrent trackers.
License: MIT
Author: Mohamed Zumair
Author-email: mhdzumair@gmail.com
Requires-Python: >=3.10
Classifier: License :: OSI Approved :: MIT License
Classifier: Programming Language :: Python :: 3
Classifier: Programming Language :: Python :: 3.10
Classifier: Programming Language :: Python :: 3.11
Classifier: Programming Language :: Python :: 3.12
Requires-Dist: aiodns (>=3.2.0,<4.0.0)
Requires-Dist: aiohttp (>=3.9.5,<4.0.0)
Requires-Dist: bencodepy (>=0.9.5,<0.10.0)
